{
  "orders": [
    {
      "email": "Devil@hell.h",
      "customer": "Someone",
      "orderType": "retail",
      "provider": "bunnyForMoney",
      "dateToDone": "30.07.19",
      "phone": "-0 000 000 000",
      "product": "people",
      "comment": "ASAP",
      "seller": "Иванов И.И.",
      "date": "06.06.18",
      "orderId": "r-1907091",
      "status": "done",
      "id": 1
    },
    {
      "email": "rqwrr@yandex.ru",
      "customer": "Adam Smith",
      "orderType": "wholesale",
      "provider": "Apple",
      "dateToDone": "25.07.19",
      "phone": "+380987185",
      "product": "Apples",
      "comment": "asfdsd",
      "seller": "Пушкин А.С.",
      "date": "29.07.18",
      "orderId": "w-1907092",
      "status": "confirm",
      "id": 2
    },
    {
      "email": "rqwrr@yandex.ru",
      "customer": "Quentin J Lambert",
      "orderType": "retail",
      "provider": "needMeat",
      "dateToDone": "29.07.19",
      "phone": "+380987185",
      "product": "Apples",
      "comment": "asfdsd",
      "seller": "Иванов И.И.",
      "date": "21.07.19",
      "orderId": "r-1907093",
      "status": "failed",
      "id": 3
    },
    {
      "email": "rqwrr@yandex.ru",
      "customer": "Quentin J Lambert",
      "orderType": "retail",
      "provider": "needMeat",
      "dateToDone": "18.07.19",
      "phone": "+380987185",
      "product": "Apples",
      "comment": "Note",
      "seller": "Иванов И.И.",
      "date": "10.07.19",
      "orderId": "r-1907105",
      "status": "confirm",
      "id": 4
    },
    {
      "email": "gasd@gasdasd",
      "customer": "Quentin J Lambert",
      "orderType": "wholesale",
      "provider": "needMeat",
      "dateToDone": "31.07.19",
      "phone": "+380987185",
      "product": "Bananas",
      "comment": "Note",
      "seller": "Иванов И.И.",
      "date": "10.07.19",
      "orderId": "w-1907106",
      "status": "done",
      "id": 5
    },
    {
      "email": "rqwrr@yandex.ru",
      "customer": "Quentin J Lambert",
      "orderType": "wholesale",
      "provider": "needMeat",
      "dateToDone": "12.07.19",
      "phone": "+380987185",
      "product": "Apples",
      "comment": "nre",
      "seller": "Иванов И.И.",
      "date": "10.07.19",
      "orderId": "w-1907109",
      "status": "done",
      "id": 6
    },
    {
      "orderType": "retail",
      "product": "Apples",
      "provider": "needMeat",
      "dateToDone": "29.08.19",
      "email": "rqwrr@yandex.ru",
      "phone": "+ 0 000 000 000",
      "orderId": "р-1907136",
      "status": "done",
      "seller": "Иванов И.И.",
      "customer": "Tony Dolly",
      "date": "13.07.19",
      "id": 7
    },
    {
      "orderType": "retail",
      "email": "rqwrr@yandex.ru",
      "phone": "+1 999 999 999",
      "product": "Bunny",
      "provider": "bunnyForMoney",
      "dateToDone": "22.08.19",
      "orderId": "р-1907137",
      "status": "done",
      "seller": "Иванов И.И.",
      "customer": "Gregor Giant",
      "date": "13.07.19",
      "id": 8
    },
    {
      "orderType": "retail",
      "dateToDone": "17.08.19",
      "provider": "needMeat",
      "product": "people",
      "phone": "+1 999 999 999",
      "email": "rqwrr@yandex.ru",
      "orderId": "р-1907138",
      "status": "confirm",
      "seller": "Иванов И.И.",
      "customer": "Louis Dolly",
      "date": "13.07.19",
      "id": 9
    }
  ]
}